tests/__init__.py
tests/tests.py
wiktionaryparserru/__init__.py
wiktionaryparserru/parser.py
wiktionaryparserru/utils.py
wiktionary_parser_ru-0.0.2.dist-info/LICENSE
wiktionary_parser_ru-0.0.2.dist-info/METADATA
wiktionary_parser_ru-0.0.2.dist-info/WHEEL
wiktionary_parser_ru-0.0.2.dist-info/top_level.txt
wiktionary_parser_ru-0.0.2.dist-info/RECORD
